{"tau_u": 6, "eps": 6.33, "lr_max": 0.04, "lr_min": 1e-06, "lr_tau": 293, "wff_const": 4.48, "wff_const_beta": 20, "wff_const_alpha": 0.94, "wff_max": 3.247, "wff_min": 1.917, "wff_tau_max": 2000, "wff_tau_min": 35, "wff_tau_tau": 250, "wff_beta": 0.81, "wr_const": 4.158, "dim": 2, "A": 0.109, "B": 0.256, "sigma_exc": 0.004, "sigma_inh": 6.518, "tau_ff": 86, "tau_rec": 84, "syn_ff_tau": 45, "syn_ff_thr": 0.555, "rate_func_beta": 1.0, "rate_func_alpha": 63, "is_lr_tau_decay": false, "is_g_decay": true, "is_syn": false, "rule": "hebb", "N": 9, "Nj": 9}